karma_game_library/__init__.py
karma_game_library/algorithms/optimizer.py
karma_game_library/algorithms/simulator.py
karma_game_library/entities/game_parameters.py
karma_game_library/entities/policy.py
karma_game_library/entities/state_distribution.py
karma_game_library/templates/__init__.py
karma_game_library/templates/cost/__init__.py
karma_game_library/templates/cost/cost.py
karma_game_library/templates/karma_redistribution/__init__.py
karma_game_library/templates/karma_redistribution/karma_redistribution.py
karma_game_library/templates/outcome/__init__.py
karma_game_library/templates/outcome/outcome.py
karma_game_library/templates/overflow_distribution/__init__.py
karma_game_library/templates/overflow_distribution/overflow_distribution.py
karma_game_library/templates/p_karma_transition/__init__.py
karma_game_library/templates/p_karma_transition/p_karma_transition.py
karma_game_library/templates/p_outcome/__init__.py
karma_game_library/templates/p_outcome/p_outcome.py
karma_game_library/templates/p_urgency_transition/__init__.py
karma_game_library/templates/p_urgency_transition/p_urgency_transition.py
karma_game_library/templates/payment/__init__.py
karma_game_library/templates/payment/payment.py
karma_game_library/templates/urgency_transition/__init__.py
karma_game_library/templates/urgency_transition/urgency_transition.py
karma_game_library/utils/check.py
karma_game_library/utils/visualizer.py
karma_game_library-1.0.2.dist-info/LICENSE
karma_game_library-1.0.2.dist-info/METADATA
karma_game_library-1.0.2.dist-info/WHEEL
karma_game_library-1.0.2.dist-info/top_level.txt
karma_game_library-1.0.2.dist-info/RECORD
