Metadata-Version: 2.1
Name: karma_game_library
Version: 1.0.2
Summary: The Karma Game Library is a powerful and rich software framework for the computation of optimal policies for rational agents and the simulation of Karma Games in scientific contexts. It is easy to use and compatible with domain specific simulators.
Author-email: Kevin Riehl <kriehl@ethz.ch>
License: GNU GENERAL PUBLIC LICENSE
Project-URL: Homepage, https://github.com/DerKevinRiehl/karma_game_library
Project-URL: Issues, https://github.com/DerKevinRiehl/karma_game_library/issues
Classifier: Programming Language :: Python :: 3
Classifier: Operating System :: OS Independent
Requires-Python: >=3.7
License-File: LICENSE
Requires-Dist: numpy >=1.25.2
Requires-Dist: matplotlib >=3.9.0
Requires-Dist: Pillow >=10.3.0
Requires-Dist: scikit-learn >=1.5.0
